magicdb/Fields/__init__.py
magicdb/Fields/location.py
magicdb/Fields/phone_number.py
magicdb/Fields/places.py
magicdb/FirestoreWrappers/BatchWrapper.py
magicdb/Models/BaseModelName.py
magicdb/Models/DateModel.py
magicdb/Models/DateModelSpeed.py
magicdb/Models/FrontendParserModel.py
magicdb/Models/MagicCache.py
magicdb/Models/MagicModel.py
magicdb/Models/MagicModelSpeed.py
magicdb/Models/ReadOnlyModel.py
magicdb/Models/RedisModel.py
magicdb/Models/RemoveFields.py
magicdb/Models/RemoveFieldsSpeed.py
magicdb/Models/SlugModel.py
magicdb/Models/TestModel.py
magicdb/Models/__init__.py
magicdb/Models/computed_fields.py
magicdb/Models/magic_fields_maker.py
magicdb/Models/magic_model_helpers.py
magicdb/Models/model_helpers.py
magicdb/Queries/Q.py
magicdb/Queries/Query.py
magicdb/Queries/QueryRedis.py
magicdb/Queries/QuerySpeed.py
magicdb/Queries/QuerySpeedNew.py
magicdb/Queries/__init__.py
magicdb/Timing/__init__.py
magicdb/Timing/decorator.py
magicdb/Timing/main.py
magicdb/__init__.py
magicdb/database/Database.py
magicdb/database/__init__.py
magicdb/utils/Redis/decorators.py
magicdb/utils/Redis/new_wrapper.py
magicdb/utils/Redis/wrapper.py
magicdb/utils/Serverless/span.py
magicdb/utils/async_helpers.py
magicdb/utils/updating_objects.py
magicdb-0.2.189.dist-info/WHEEL
magicdb-0.2.189.dist-info/METADATA
magicdb-0.2.189.dist-info/RECORD
