Metadata-Version: 2.1
Name: magicdb
Version: 0.2.189
Summary: 
Home-page: https://github.com/jerber/magicdb_new
Keywords: firestore,pydantic,orm,python orm firestore,firebase
Author: Jeremy Berman
Author-email: jerber@sas.upenn.edu
Requires-Python: >=3.8,<4.0
Classifier: Programming Language :: Python :: 3
Classifier: Programming Language :: Python :: 3.8
Requires-Dist: firebase-admin (>=4.4.0,<5.0.0)
Requires-Dist: glom (>=20.8.0,<21.0.0)
Requires-Dist: grpcio (>=1.37.0,<2.0.0)
Requires-Dist: phonenumbers (>=8.12.19,<9.0.0)
Requires-Dist: pydantic (>=1.7.3,<2.0.0)
Requires-Dist: python-google-places (>=1.4.2,<2.0.0)
Requires-Dist: python-slugify (>=4.0.1,<5.0.0)
Requires-Dist: redis (>=3.5.3,<4.0.0)
Requires-Dist: ujson (>=3.0.0)
Project-URL: Repository, https://github.com/jerber/magicdb_new
